parallel_loading/__init__.py
parallel_loading-0.1.1.dist-info/WHEEL
parallel_loading-0.1.1.dist-info/METADATA
parallel_loading-0.1.1.dist-info/RECORD
